LICENSE
README.rst
pyproject.toml
sendoff/__init__.py
sendoff/ctable.py
sendoff/sdblock.py
sendoff-0.1.6.dist-info/LICENSE
sendoff-0.1.6.dist-info/WHEEL
sendoff-0.1.6.dist-info/METADATA
sendoff-0.1.6.dist-info/RECORD
