Metadata-Version: 2.1
Name: sendoff
Version: 0.1.6
Summary: The minimal SDF metadata parser
Home-page: https://github.com/pechersky/sendoff
License: MIT
Author: Yakov Pechersky
Author-email: ypechersky@treeline.bio
Requires-Python: >=3.8,<4.0
Classifier: License :: OSI Approved :: MIT License
Classifier: Programming Language :: Python :: 3
Classifier: Programming Language :: Python :: 3.8
Classifier: Programming Language :: Python :: 3.9
Classifier: Programming Language :: Python :: 3.10
Classifier: Programming Language :: Python :: 3.11
Provides-Extra: test
Project-URL: Repository, https://github.com/pechersky/sendoff
